[
  {
    "EmployeeID": 2216,
    "LoginID": "700001275",
    "FirstName": "dd",
    "LastName": "K",
    "StartDate": "2025-03-05T07:47:37.217",
    "Organization": "Benchmark",
    "Location": "Bangalore",
    "Title": "Associate",
    "Email": "div@gmail.com",
    "IsActive": "1",
    "Phone": "9988998800",
    "supervisor": null
  },
  {
    "EmployeeID": 125531,
    "LoginID": "1234",
    "FirstName": "Duke",
    "LastName": "Stark",
    "StartDate": "2021-06-24T00:00:00",
    "Organization": "Benchmark ESG",
    "Location": "Bangalore",
    "Title": "Trainee",
    "Email": "tony.stark@gmail.com",
    "IsActive": "0",
    "Phone": "1235678763",
    "supervisor": null
  },
  {
    "EmployeeID": 125594,
    "LoginID": "1234576543",
    "FirstName": "hello",
    "LastName": "Ishitatest",
    "StartDate": "2021-06-30T00:00:00",
    "Organization": "Benchmark ESG",
    "Location": "Bangalore",
    "Title": "Product Developer",
    "Email": "hello@gmail.com",
    "IsActive": "1",
    "Phone": "4567907612",
    "supervisor": null
  },
  {
    "EmployeeID": 125595,
    "LoginID": "12345",
    "FirstName": "James",
    "LastName": "Bond",
    "StartDate": "2021-06-04T00:00:00",
    "Organization": "Benchmark ESG",
    "Location": "Bangalore",
    "Title": "Trainee",
    "Email": "test@exae.com",
    "IsActive": "1",
    "Phone": "7564398576",
    "supervisor": null
  },
  {
    "EmployeeID": 125597,
    "LoginID": "888",
    "FirstName": "",
    "LastName": "",
    "StartDate": "1900-01-01T00:00:00",
    "Organization": "Benchmark ESG",
    "Location": "Bangalore",
    "Title": "",
    "Email": "",
    "IsActive": "0",
    "Phone": "5628476901",
    "supervisor": ""
  },
  {
    "EmployeeID": 125598,
    "LoginID": "888",
    "FirstName": "Ram",
    "LastName": "Sharma",
    "StartDate": "2021-06-11T00:00:00",
    "Organization": "Benchmark ESG",
    "Location": "Bangalore",
    "Title": "Associate",
    "Email": "ram22@gmail.com",
    "IsActive": "1",
    "Phone": "5628476901",
    "supervisor": null
  },
  {
    "EmployeeID": 125599,
    "LoginID": "12",
    "FirstName": "Steve",
    "LastName": "Stark",
    "StartDate": "2021-05-05T00:00:00",
    "Organization": "Benchmark ESG",
    "Location": "Bangalore",
    "Title": "Trainee",
    "Email": "ss@gmail.com",
    "IsActive": "1",
    "Phone": "9812639865",
    "supervisor": null
  },
  {
    "EmployeeID": 125600,
    "LoginID": "12",
    "FirstName": "Steve",
    "LastName": "Stark",
    "StartDate": "2021-05-05T00:00:00",
    "Organization": "Benchmark ESG",
    "Location": "Bangalore",
    "Title": "Trainee",
    "Email": "ss@gmail.com",
    "IsActive": "1",
    "Phone": "9812639865",
    "supervisor": null
  },
  {
    "EmployeeID": 125603,
    "LoginID": "219",
    "FirstName": "John",
    "LastName": "",
    "StartDate": "2021-06-29T00:00:00",
    "Organization": "Benchmark ESG",
    "Location": "Bangalore",
    "Title": "Trainee",
    "Email": "john@gmail.com",
    "IsActive": "1",
    "Phone": "4567328907",
    "supervisor": null
  },
  {
    "EmployeeID": 125610,
    "LoginID": "104",
    "FirstName": "James",
    "LastName": "",
    "StartDate": "2021-07-01T00:00:00",
    "Organization": "Benchmark ESG",
    "Location": "Bangalore",
    "Title": "Trainee",
    "Email": "jj@gmail.com",
    "IsActive": "1",
    "Phone": "1234567899",
    "supervisor": null
  },
  {
    "EmployeeID": 125618,
    "LoginID": "598123",
    "FirstName": "Jasper",
    "LastName": "",
    "StartDate": "2021-07-01T00:00:00",
    "Organization": "Benchmark ESG",
    "Location": "Bangalore",
    "Title": "Trainee",
    "Email": "test@j.com",
    "IsActive": "1",
    "Phone": "5678923456",
    "supervisor": null
  },
  {
    "EmployeeID": 125639,
    "LoginID": "786905",
    "FirstName": "Sutton",
    "LastName": "",
    "StartDate": "2021-07-13T00:00:00",
    "Organization": "Benchmark ESG",
    "Location": "Bangalore",
    "Title": "",
    "Email": "hello@gmail.com",
    "IsActive": "1",
    "Phone": "3456846898",
    "supervisor": null
  },
  {
    "EmployeeID": 125644,
    "LoginID": "12778",
    "FirstName": "Clark",
    "LastName": "Kent",
    "StartDate": "2024-11-15T00:00:00",
    "Organization": "Benchmark ESG",
    "Location": "Bangalore",
    "Title": "HR",
    "Email": "v@123",
    "IsActive": "1",
    "Phone": "6562637786",
    "supervisor": null
  },
  {
    "EmployeeID": 125646,
    "LoginID": "67978",
    "FirstName": "Ram",
    "LastName": "Sharma",
    "StartDate": "2021-07-27T00:00:00",
    "Organization": "Benchmark ESG",
    "Location": "Bangalore",
    "Title": "",
    "Email": "v@123",
    "IsActive": "1",
    "Phone": "5875872579",
    "supervisor": null
  },
  {
    "EmployeeID": 125650,
    "LoginID": "45696",
    "FirstName": "Tony",
    "LastName": "Stark",
    "StartDate": "2021-08-02T00:00:00",
    "Organization": "Benchmark ESG",
    "Location": "Bangalore",
    "Title": "Trainee",
    "Email": "tony.stark@gmail.com",
    "IsActive": "1",
    "Phone": "2365739275",
    "supervisor": null
  },
  {
    "EmployeeID": 125662,
    "LoginID": "2344",
    "FirstName": "man",
    "LastName": "Vaiiiiiiiiiiiiiii",
    "StartDate": "2021-08-18T00:00:00",
    "Organization": "Benchmark ESG",
    "Location": "Bangalore",
    "Title": "ttp",
    "Email": "man@123",
    "IsActive": "1",
    "Phone": "7827367566",
    "supervisor": null
  },
  {
    "EmployeeID": 125665,
    "LoginID": "1426",
    "FirstName": "man",
    "LastName": "Sapien",
    "StartDate": "2021-08-06T00:00:00",
    "Organization": "Benchmark ESG",
    "Location": "Bangalore",
    "Title": "No madic",
    "Email": "man@123",
    "IsActive": "0",
    "Phone": "8762877652",
    "supervisor": null
  },
  {
    "EmployeeID": 125673,
    "LoginID": "7995691526",
    "FirstName": "Sunil",
    "LastName": "Allu",
    "StartDate": "2021-08-25T00:00:00",
    "Organization": "Benchmark ESG",
    "Location": "Bangalore",
    "Title": "Associate",
    "Email": "allurukarthik01@gmail.com",
    "IsActive": "1",
    "Phone": "",
    "supervisor": null
  },
  {
    "EmployeeID": 125684,
    "LoginID": "9486758",
    "FirstName": "Tony",
    "LastName": "Parker",
    "StartDate": "2021-09-09T00:00:00",
    "Organization": "Benchmark ESG",
    "Location": "Bangalore",
    "Title": "Trainee",
    "Email": "tony.stark@gmail.com",
    "IsActive": "1",
    "Phone": "3456789098",
    "supervisor": null
  },
  {
    "EmployeeID": 125689,
    "LoginID": "321",
    "FirstName": "naruto",
    "LastName": "uzumaki",
    "StartDate": "2021-09-20T06:16:27.86",
    "Organization": "Benchmark ESG",
    "Location": "Bangalore",
    "Title": "Associate",
    "Email": "naruto@gmail.com",
    "IsActive": "1",
    "Phone": "123123",
    "supervisor": null
  },
  {
    "EmployeeID": 125690,
    "LoginID": "12333",
    "FirstName": "rich",
    "LastName": "rak",
    "StartDate": "2017-01-05T00:00:00",
    "Organization": "Benchmark ESG",
    "Location": "Bangalore",
    "Title": "Associate",
    "Email": "richo@gmail.com",
    "IsActive": "1",
    "Phone": "12313",
    "supervisor": null
  },
  {
    "EmployeeID": 125691,
    "LoginID": "12332",
    "FirstName": "Tom",
    "LastName": "cruise",
    "StartDate": "2021-09-21T03:28:58.953",
    "Organization": "Benchmark ESG",
    "Location": "Bangalore",
    "Title": null,
    "Email": "tom@gmail.com",
    "IsActive": "1",
    "Phone": "123444",
    "supervisor": null
  },
  {
    "EmployeeID": 125694,
    "LoginID": "123211",
    "FirstName": "Ferry",
    "LastName": "furnadis",
    "StartDate": "2021-09-21T05:02:25.217",
    "Organization": "Benchmark ESG",
    "Location": "Bangalore",
    "Title": null,
    "Email": "tom@gmail.com",
    "IsActive": "1",
    "Phone": "123444",
    "supervisor": null
  },
  {
    "EmployeeID": 125696,
    "LoginID": "6767545432",
    "FirstName": "gd",
    "LastName": "",
    "StartDate": "2021-09-09T00:00:00",
    "Organization": "Benchmark ESG",
    "Location": "Bangalore",
    "Title": "Associate",
    "Email": "tes*t@gmail",
    "IsActive": "1",
    "Phone": null,
    "supervisor": null
  },
  {
    "EmployeeID": 125697,
    "LoginID": "6767545432",
    "FirstName": "gd",
    "LastName": "",
    "StartDate": "2021-09-09T00:00:00",
    "Organization": "Benchmark ESG",
    "Location": "Bangalore",
    "Title": "Associate",
    "Email": "tes*t@gmail",
    "IsActive": "1",
    "Phone": null,
    "supervisor": null
  },
  {
    "EmployeeID": 125698,
    "LoginID": "6767545432",
    "FirstName": "gd",
    "LastName": "",
    "StartDate": "2021-09-09T00:00:00",
    "Organization": "Benchmark ESG",
    "Location": "Bangalore",
    "Title": "Associate",
    "Email": "tes*t@gmail",
    "IsActive": "1",
    "Phone": null,
    "supervisor": null
  },
  {
    "EmployeeID": 125699,
    "LoginID": "6767675454",
    "FirstName": "ec",
    "LastName": "",
    "StartDate": "2021-09-14T00:00:00",
    "Organization": "Benchmark ESG",
    "Location": "Bangalore",
    "Title": "Associate",
    "Email": "abc@gmail",
    "IsActive": "1",
    "Phone": null,
    "supervisor": null
  },
  {
    "EmployeeID": 125700,
    "LoginID": "6767675454",
    "FirstName": "ec",
    "LastName": "",
    "StartDate": "2021-09-14T00:00:00",
    "Organization": "Benchmark ESG",
    "Location": "Bangalore",
    "Title": "Associate",
    "Email": "abc@gmail",
    "IsActive": "1",
    "Phone": null,
    "supervisor": null
  },
  {
    "EmployeeID": 125701,
    "LoginID": "7897896543",
    "FirstName": "ty",
    "LastName": "",
    "StartDate": "2021-09-06T00:00:00",
    "Organization": "Benchmark ESG",
    "Location": "Bangalore",
    "Title": "Associate",
    "Email": "abc@gmail",
    "IsActive": "1",
    "Phone": null,
    "supervisor": null
  },
  {
    "EmployeeID": 125705,
    "LoginID": "5678",
    "FirstName": "Jiya",
    "LastName": "Pise",
    "StartDate": "2020-08-03T00:00:00",
    "Organization": "Benchmark ESG",
    "Location": "Bangalore",
    "Title": "Tester",
    "Email": "test16@gmail.com",
    "IsActive": "1",
    "Phone": "7896543210",
    "supervisor": null
  },
  {
    "EmployeeID": 125706,
    "LoginID": "7890",
    "FirstName": "mina",
    "LastName": "Shahane",
    "StartDate": "2021-05-31T00:00:00",
    "Organization": "Benchmark ESG",
    "Location": "Bangalore",
    "Title": "Hr",
    "Email": "test17@gmail.com",
    "IsActive": "1",
    "Phone": "7689543021",
    "supervisor": null
  },
  {
    "EmployeeID": 125710,
    "LoginID": "7890",
    "FirstName": "batman",
    "LastName": "Pise",
    "StartDate": "2021-05-31T00:00:00",
    "Organization": "Benchmark ESG",
    "Location": "Bangalore",
    "Title": "Hr",
    "Email": "test19@gmail.com",
    "IsActive": "1",
    "Phone": "7689543021",
    "supervisor": null
  },
  {
    "EmployeeID": 125716,
    "LoginID": "7995691526",
    "FirstName": "Marry",
    "LastName": "Allu",
    "StartDate": "2021-09-28T00:00:00",
    "Organization": "Benchmark ESG",
    "Location": "Bangalore",
    "Title": "Associate",
    "Email": "allurukarthik01@gmail.com",
    "IsActive": "1",
    "Phone": "",
    "supervisor": null
  },
  {
    "EmployeeID": 125717,
    "LoginID": "7995691526",
    "FirstName": "Karthik Karthik",
    "LastName": "Allu",
    "StartDate": "2021-09-28T00:00:00",
    "Organization": "Benchmark ESG",
    "Location": "Bangalore",
    "Title": "Associate",
    "Email": "allurukarthik01@gmail.com",
    "IsActive": "1",
    "Phone": "",
    "supervisor": null
  },
  {
    "EmployeeID": 125724,
    "LoginID": "",
    "FirstName": "Shreya",
    "LastName": "Shahane",
    "StartDate": null,
    "Organization": "Benchmark ESG",
    "Location": "Bangalore",
    "Title": "",
    "Email": "shreya@gmail.com",
    "IsActive": "1",
    "Phone": "7689054321",
    "supervisor": null
  },
  {
    "EmployeeID": 125731,
    "LoginID": "7995691526",
    "FirstName": "Karthik",
    "LastName": "Allu",
    "StartDate": "2021-10-01T00:00:00",
    "Organization": "Benchmark ESG",
    "Location": "Bangalore",
    "Title": "Associate",
    "Email": "allurukarthik01@gmail.com",
    "IsActive": "1",
    "Phone": null,
    "supervisor": null
  },
  {
    "EmployeeID": 125748,
    "LoginID": null,
    "FirstName": "mira",
    "LastName": null,
    "StartDate": null,
    "Organization": "Benchmark ESG",
    "Location": "Bangalore",
    "Title": null,
    "Email": null,
    "IsActive": "1",
    "Phone": null,
    "supervisor": null
  },
  {
    "EmployeeID": 125761,
    "LoginID": null,
    "FirstName": "siya",
    "LastName": "mishra",
    "StartDate": null,
    "Organization": "Benchmark ESG",
    "Location": "Bangalore",
    "Title": "Product Developer",
    "Email": "siya@gmail.com",
    "IsActive": "1",
    "Phone": null,
    "supervisor": null
  },
  {
    "EmployeeID": 125762,
    "LoginID": null,
    "FirstName": "diya",
    "LastName": "park",
    "StartDate": null,
    "Organization": "Benchmark ESG",
    "Location": "Bangalore",
    "Title": "Product Developer",
    "Email": "s@gmail.com",
    "IsActive": "1",
    "Phone": null,
    "supervisor": null
  },
  {
    "EmployeeID": 125766,
    "LoginID": null,
    "FirstName": "riya",
    "LastName": "park",
    "StartDate": null,
    "Organization": "Benchmark ESG",
    "Location": "Bangalore",
    "Title": "Product Developer",
    "Email": "riya@gmail.com",
    "IsActive": "1",
    "Phone": null,
    "supervisor": null
  },
  {
    "EmployeeID": 125773,
    "LoginID": "4545676789",
    "FirstName": "Nisarga",
    "LastName": "ert",
    "StartDate": "2021-09-29T00:00:00",
    "Organization": "Benchmark ESG",
    "Location": "Bangalore",
    "Title": "Trainee",
    "Email": "abc@gmail",
    "IsActive": "1",
    "Phone": null,
    "supervisor": null
  },
  {
    "EmployeeID": 125784,
    "LoginID": "1234576543",
    "FirstName": "hello",
    "LastName": "Ishitatest56",
    "StartDate": "2021-06-30T00:00:00",
    "Organization": "Benchmark ESG",
    "Location": "Bangalore",
    "Title": "Product Developer",
    "Email": "hello@gmail.com",
    "IsActive": "1",
    "Phone": null,
    "supervisor": null
  },
  {
    "EmployeeID": 125806,
    "LoginID": "7995691526",
    "FirstName": "Karthik",
    "LastName": "m",
    "StartDate": "2021-10-19T00:00:00",
    "Organization": "Benchmark ESG",
    "Location": "Bangalore",
    "Title": "Associate",
    "Email": "allurukarthik01@gmail.com",
    "IsActive": "1",
    "Phone": "1234567897",
    "supervisor": null
  },
  {
    "EmployeeID": 125820,
    "LoginID": null,
    "FirstName": "kiyara",
    "LastName": "desoza",
    "StartDate": null,
    "Organization": "Benchmark ESG",
    "Location": "Bangalore",
    "Title": "Product Developer",
    "Email": "kiyara@gmail.com",
    "IsActive": "1",
    "Phone": null,
    "supervisor": null
  },
  {
    "EmployeeID": 125827,
    "LoginID": null,
    "FirstName": "mona",
    "LastName": "a",
    "StartDate": null,
    "Organization": "Benchmark ESG",
    "Location": "Bangalore",
    "Title": "Product Developer",
    "Email": "mona@gmail.com",
    "IsActive": "1",
    "Phone": null,
    "supervisor": null
  },
  {
    "EmployeeID": 125836,
    "LoginID": null,
    "FirstName": "jonny",
    "LastName": "abc",
    "StartDate": null,
    "Organization": "Benchmark ESG",
    "Location": "Bangalore",
    "Title": "Associate",
    "Email": "abc@gmail.com",
    "IsActive": "1",
    "Phone": null,
    "supervisor": null
  },
  {
    "EmployeeID": 125838,
    "LoginID": null,
    "FirstName": "john",
    "LastName": "abc",
    "StartDate": null,
    "Organization": "Benchmark ESG",
    "Location": "Bangalore",
    "Title": "Product Developer",
    "Email": "abc@gmail.com",
    "IsActive": "1",
    "Phone": null,
    "supervisor": null
  },
  {
    "EmployeeID": 125856,
    "LoginID": null,
    "FirstName": "jonny",
    "LastName": "k",
    "StartDate": null,
    "Organization": "Benchmark ESG",
    "Location": "Bangalore",
    "Title": "Associate",
    "Email": "jonny@gmail.com",
    "IsActive": "1",
    "Phone": null,
    "supervisor": null
  },
  {
    "EmployeeID": 125860,
    "LoginID": null,
    "FirstName": "diya",
    "LastName": "desoza",
    "StartDate": null,
    "Organization": "Benchmark ESG",
    "Location": "Bangalore",
    "Title": "Product Developer",
    "Email": "abc@gmail.com",
    "IsActive": "1",
    "Phone": null,
    "supervisor": null
  },
  {
    "EmployeeID": 125861,
    "LoginID": null,
    "FirstName": "gita",
    "LastName": "park",
    "StartDate": null,
    "Organization": "Benchmark ESG",
    "Location": "Bangalore",
    "Title": "Associate",
    "Email": "gita@gmail.com",
    "IsActive": "1",
    "Phone": null,
    "supervisor": null
  },
  {
    "EmployeeID": 125878,
    "LoginID": "0077",
    "FirstName": "Tony",
    "LastName": "Stark",
    "StartDate": "2021-06-12T00:00:00",
    "Organization": "Benchmark ESG",
    "Location": "Bangalore",
    "Title": "Trainee",
    "Email": "tony.stark@gmail.com",
    "IsActive": "1",
    "Phone": "",
    "supervisor": null
  },
  {
    "EmployeeID": 125884,
    "LoginID": null,
    "FirstName": "Tony",
    "LastName": "Stark",
    "StartDate": "2021-06-24T00:00:00",
    "Organization": "Benchmark ESG",
    "Location": "Bangalore",
    "Title": "Trainee",
    "Email": "tony.stark@gmail.com",
    "IsActive": "1",
    "Phone": null,
    "supervisor": null
  },
  {
    "EmployeeID": 125885,
    "LoginID": null,
    "FirstName": "Tony",
    "LastName": "Stark",
    "StartDate": "2021-06-24T00:00:00",
    "Organization": "Benchmark ESG",
    "Location": "Bangalore",
    "Title": "Trainee",
    "Email": "tony.stark@gmail.com",
    "IsActive": "1",
    "Phone": null,
    "supervisor": null
  },
  {
    "EmployeeID": 125886,
    "LoginID": null,
    "FirstName": "Tony",
    "LastName": "Stark",
    "StartDate": "2021-06-24T00:00:00",
    "Organization": "Benchmark ESG",
    "Location": "Bangalore",
    "Title": "Trainee",
    "Email": "tony.stark@gmail.com",
    "IsActive": "1",
    "Phone": null,
    "supervisor": null
  },
  {
    "EmployeeID": 125887,
    "LoginID": null,
    "FirstName": "Tony",
    "LastName": "Stark",
    "StartDate": "2021-06-24T00:00:00",
    "Organization": "Benchmark ESG",
    "Location": "Bangalore",
    "Title": "Trainee",
    "Email": "tony.stark@gmail.com",
    "IsActive": "1",
    "Phone": null,
    "supervisor": null
  },
  {
    "EmployeeID": 125888,
    "LoginID": null,
    "FirstName": "Tony",
    "LastName": "Stark",
    "StartDate": "2021-06-24T00:00:00",
    "Organization": "Benchmark ESG",
    "Location": "Bangalore",
    "Title": "Trainee",
    "Email": "tony.stark@gmail.com",
    "IsActive": "1",
    "Phone": null,
    "supervisor": null
  },
  {
    "EmployeeID": 125889,
    "LoginID": null,
    "FirstName": "Tony",
    "LastName": "Stark",
    "StartDate": "2021-06-24T00:00:00",
    "Organization": "Benchmark ESG",
    "Location": "Bangalore",
    "Title": "Trainee",
    "Email": "tony.stark@gmail.com",
    "IsActive": "1",
    "Phone": null,
    "supervisor": null
  },
  {
    "EmployeeID": 125890,
    "LoginID": null,
    "FirstName": "Tony",
    "LastName": "Stark",
    "StartDate": "2021-06-24T00:00:00",
    "Organization": "Benchmark ESG",
    "Location": "Bangalore",
    "Title": "Trainee",
    "Email": "tony.stark@gmail.com",
    "IsActive": "1",
    "Phone": null,
    "supervisor": null
  },
  {
    "EmployeeID": 125891,
    "LoginID": null,
    "FirstName": "Tony",
    "LastName": "Stark",
    "StartDate": "2021-06-24T00:00:00",
    "Organization": "Benchmark ESG",
    "Location": "Bangalore",
    "Title": "Trainee",
    "Email": "tony.stark@gmail.com",
    "IsActive": "1",
    "Phone": null,
    "supervisor": null
  },
  {
    "EmployeeID": 125893,
    "LoginID": null,
    "FirstName": "Tony",
    "LastName": "Stark",
    "StartDate": "2021-06-24T00:00:00",
    "Organization": "Benchmark ESG",
    "Location": "Bangalore",
    "Title": "Trainee",
    "Email": "tony.stark@gmail.com",
    "IsActive": "1",
    "Phone": null,
    "supervisor": null
  },
  {
    "EmployeeID": 125903,
    "LoginID": "123456",
    "FirstName": "Tony",
    "LastName": "Stark",
    "StartDate": "2021-06-28T00:00:00",
    "Organization": "Benchmark ESG",
    "Location": "Bangalore",
    "Title": "Trainee",
    "Email": "tony.stark@gmail.com",
    "IsActive": "1",
    "Phone": null,
    "supervisor": null
  },
  {
    "EmployeeID": 125904,
    "LoginID": "123456",
    "FirstName": "Tony",
    "LastName": "Stark",
    "StartDate": "2021-06-28T00:00:00",
    "Organization": "Benchmark ESG",
    "Location": "Bangalore",
    "Title": "Trainee",
    "Email": "tony.stark11@gmail.com",
    "IsActive": "1",
    "Phone": null,
    "supervisor": null
  },
  {
    "EmployeeID": 125912,
    "LoginID": "1234576543",
    "FirstName": "hello",
    "LastName": "Ishitatest56",
    "StartDate": "2021-06-30T00:00:00",
    "Organization": "Benchmark ESG",
    "Location": "Bangalore",
    "Title": "Product Developer",
    "Email": "hello@gmail.com",
    "IsActive": "1",
    "Phone": null,
    "supervisor": null
  },
  {
    "EmployeeID": 125929,
    "LoginID": "123",
    "FirstName": "yes ok ",
    "LastName": "nono",
    "StartDate": "1900-01-01T00:00:00",
    "Organization": "Benchmark ESG",
    "Location": "Bangalore",
    "Title": "",
    "Email": "yesokno@gmail.com",
    "IsActive": "1",
    "Phone": null,
    "supervisor": null
  },
  {
    "EmployeeID": 125938,
    "LoginID": "",
    "FirstName": "",
    "LastName": "venky",
    "StartDate": "1900-01-01T00:00:00",
    "Organization": "Benchmark ESG",
    "Location": "Bangalore",
    "Title": "PDT",
    "Email": "santhoshvenky743@gmail.com",
    "IsActive": "1",
    "Phone": "8197757513",
    "supervisor": null
  },
  {
    "EmployeeID": 125940,
    "LoginID": "12345",
    "FirstName": "James",
    "LastName": "Bond",
    "StartDate": "2021-06-04T00:00:00",
    "Organization": "Benchmark ESG",
    "Location": "Bangalore",
    "Title": "Trainee",
    "Email": "test@exae.com",
    "IsActive": "1",
    "Phone": "7564398576",
    "supervisor": null
  },
  {
    "EmployeeID": 125942,
    "LoginID": "888",
    "FirstName": "Ram",
    "LastName": "Sharma",
    "StartDate": "2021-06-11T00:00:00",
    "Organization": "Benchmark ESG",
    "Location": "Bangalore",
    "Title": "Associate",
    "Email": "ram22@gmail.com",
    "IsActive": "1",
    "Phone": "5628476901",
    "supervisor": null
  },
  {
    "EmployeeID": 125943,
    "LoginID": "888",
    "FirstName": "Ram",
    "LastName": "Sharma",
    "StartDate": "2021-06-11T00:00:00",
    "Organization": "Benchmark ESG",
    "Location": "Bangalore",
    "Title": "Associate",
    "Email": "ram22@gmail.com",
    "IsActive": "1",
    "Phone": "5628476901",
    "supervisor": null
  },
  {
    "EmployeeID": 125944,
    "LoginID": "12",
    "FirstName": "Steve",
    "LastName": "Stark",
    "StartDate": "2021-05-05T00:00:00",
    "Organization": "Benchmark ESG",
    "Location": "Bangalore",
    "Title": "Trainee",
    "Email": "ss@gmail.com",
    "IsActive": "1",
    "Phone": "9812639865",
    "supervisor": null
  },
  {
    "EmployeeID": 125945,
    "LoginID": "12",
    "FirstName": "Steve",
    "LastName": "Stark",
    "StartDate": "2021-05-05T00:00:00",
    "Organization": "Benchmark ESG",
    "Location": "Bangalore",
    "Title": "Trainee",
    "Email": "ss@gmail.com",
    "IsActive": "1",
    "Phone": "9812639865",
    "supervisor": null
  },
  {
    "EmployeeID": 125948,
    "LoginID": "219",
    "FirstName": "John",
    "LastName": "",
    "StartDate": "2021-06-29T00:00:00",
    "Organization": "Benchmark ESG",
    "Location": "Bangalore",
    "Title": "Trainee",
    "Email": "john@gmail.com",
    "IsActive": "1",
    "Phone": "4567328907",
    "supervisor": null
  },
  {
    "EmployeeID": 125955,
    "LoginID": "104",
    "FirstName": "James",
    "LastName": "",
    "StartDate": "2021-07-01T00:00:00",
    "Organization": "Benchmark ESG",
    "Location": "Bangalore",
    "Title": "Trainee",
    "Email": "jj@gmail.com",
    "IsActive": "1",
    "Phone": "1234567899",
    "supervisor": null
  },
  {
    "EmployeeID": 125962,
    "LoginID": "598123",
    "FirstName": "Jasper",
    "LastName": "",
    "StartDate": "2021-07-01T00:00:00",
    "Organization": "Benchmark ESG",
    "Location": "Bangalore",
    "Title": "Trainee",
    "Email": "test@j.com",
    "IsActive": "1",
    "Phone": "5678923456",
    "supervisor": null
  },
  {
    "EmployeeID": 125966,
    "LoginID": "578374",
    "FirstName": "James",
    "LastName": "",
    "StartDate": "2021-07-02T00:00:00",
    "Organization": "Benchmark ESG",
    "Location": "Bangalore",
    "Title": "Trainee",
    "Email": "james@gmail.com",
    "IsActive": "1",
    "Phone": "4567893456",
    "supervisor": null
  },
  {
    "EmployeeID": 125970,
    "LoginID": "68786",
    "FirstName": "Jasper",
    "LastName": "",
    "StartDate": "2021-06-27T00:00:00",
    "Organization": "Benchmark ESG",
    "Location": "Bangalore",
    "Title": "Trainee",
    "Email": "test@james.com",
    "IsActive": "1",
    "Phone": "4567891234",
    "supervisor": null
  },
  {
    "EmployeeID": 125978,
    "LoginID": "867898",
    "FirstName": "James",
    "LastName": "",
    "StartDate": "2021-07-05T00:00:00",
    "Organization": "Benchmark ESG",
    "Location": "Bangalore",
    "Title": "Trainee",
    "Email": "james@gmail.com",
    "IsActive": "1",
    "Phone": "4563826583",
    "supervisor": null
  },
  {
    "EmployeeID": 125983,
    "LoginID": "786905",
    "FirstName": "Sutton",
    "LastName": "",
    "StartDate": "2021-07-13T00:00:00",
    "Organization": "Benchmark ESG",
    "Location": "Bangalore",
    "Title": "",
    "Email": "hello@gmail.com",
    "IsActive": "1",
    "Phone": "3456846898",
    "supervisor": null
  },
  {
    "EmployeeID": 125988,
    "LoginID": "127",
    "FirstName": "Clark",
    "LastName": "Kent",
    "StartDate": null,
    "Organization": "Benchmark ESG",
    "Location": "Bangalore",
    "Title": null,
    "Email": null,
    "IsActive": "1",
    "Phone": null,
    "supervisor": null
  },
  {
    "EmployeeID": 125989,
    "LoginID": "127",
    "FirstName": "Clark",
    "LastName": "Kent",
    "StartDate": null,
    "Organization": "Benchmark ESG",
    "Location": "Bangalore",
    "Title": null,
    "Email": null,
    "IsActive": "1",
    "Phone": null,
    "supervisor": null
  },
  {
    "EmployeeID": 125990,
    "LoginID": "679",
    "FirstName": "Ram",
    "LastName": "Sharma",
    "StartDate": "2021-07-27T02:54:58.763",
    "Organization": "Benchmark ESG",
    "Location": "Bangalore",
    "Title": null,
    "Email": null,
    "IsActive": "1",
    "Phone": null,
    "supervisor": null
  },
  {
    "EmployeeID": 125991,
    "LoginID": "1232",
    "FirstName": "eff",
    "LastName": "ddd",
    "StartDate": "2021-07-26T00:00:00",
    "Organization": "Benchmark ESG",
    "Location": "Bangalore",
    "Title": "test",
    "Email": "giri.prasanth@gensuitellc",
    "IsActive": "1",
    "Phone": null,
    "supervisor": null
  },
  {
    "EmployeeID": 125993,
    "LoginID": "45696",
    "FirstName": "Tony",
    "LastName": "Stark",
    "StartDate": "2021-08-02T00:00:00",
    "Organization": "Benchmark ESG",
    "Location": "Bangalore",
    "Title": "Trainee",
    "Email": "tony.stark@gmail.com",
    "IsActive": "1",
    "Phone": "2365739275",
    "supervisor": null
  },
  {
    "EmployeeID": 126004,
    "LoginID": null,
    "FirstName": "gen",
    "LastName": null,
    "StartDate": "2021-08-18T11:23:38.7",
    "Organization": "Benchmark ESG",
    "Location": "Bangalore",
    "Title": null,
    "Email": null,
    "IsActive": "1",
    "Phone": null,
    "supervisor": null
  },
  {
    "EmployeeID": 126005,
    "LoginID": null,
    "FirstName": "man",
    "LastName": null,
    "StartDate": "2021-08-18T11:35:19.713",
    "Organization": "Benchmark ESG",
    "Location": "Bangalore",
    "Title": null,
    "Email": null,
    "IsActive": "1",
    "Phone": null,
    "supervisor": null
  },
  {
    "EmployeeID": 126006,
    "LoginID": "5679",
    "FirstName": "gen",
    "LastName": "maxewell",
    "StartDate": "2021-08-06T00:00:00",
    "Organization": "Benchmark ESG",
    "Location": "Bangalore",
    "Title": "BDA",
    "Email": "Lj@1",
    "IsActive": "1",
    "Phone": "567890976",
    "supervisor": null
  },
  {
    "EmployeeID": 126007,
    "LoginID": null,
    "FirstName": "gen",
    "LastName": null,
    "StartDate": "2021-08-18T11:23:38.7",
    "Organization": "Benchmark ESG",
    "Location": "Bangalore",
    "Title": null,
    "Email": null,
    "IsActive": "1",
    "Phone": null,
    "supervisor": null
  },
  {
    "EmployeeID": 126008,
    "LoginID": null,
    "FirstName": "man",
    "LastName": null,
    "StartDate": "2021-08-18T11:35:19.713",
    "Organization": "Benchmark ESG",
    "Location": "Bangalore",
    "Title": null,
    "Email": null,
    "IsActive": "1",
    "Phone": null,
    "supervisor": null
  },
  {
    "EmployeeID": 126009,
    "LoginID": "6789",
    "FirstName": "glen",
    "LastName": "mark",
    "StartDate": "2022-08-06T00:00:00",
    "Organization": "Benchmark ESG",
    "Location": "Bangalore",
    "Title": "HR",
    "Email": "glen@123",
    "IsActive": "1",
    "Phone": "1234567898",
    "supervisor": null
  },
  {
    "EmployeeID": 126010,
    "LoginID": null,
    "FirstName": "gd",
    "LastName": null,
    "StartDate": "2019-06-06T00:00:00",
    "Organization": "Benchmark ESG",
    "Location": "Bangalore",
    "Title": null,
    "Email": null,
    "IsActive": "1",
    "Phone": null,
    "supervisor": null
  },
  {
    "EmployeeID": 126011,
    "LoginID": null,
    "FirstName": "Parker",
    "LastName": null,
    "StartDate": "2020-06-05T00:00:00",
    "Organization": "Benchmark ESG",
    "Location": "Bangalore",
    "Title": null,
    "Email": null,
    "IsActive": "1",
    "Phone": null,
    "supervisor": null
  },
  {
    "EmployeeID": 126013,
    "LoginID": "12345",
    "FirstName": "gen",
    "LastName": "dxcv",
    "StartDate": "2021-08-18T00:00:00",
    "Organization": "Benchmark ESG",
    "Location": "Bangalore",
    "Title": "hr",
    "Email": "V@3sdfgCtY12",
    "IsActive": "1",
    "Phone": "1234567890",
    "supervisor": null
  },
  {
    "EmployeeID": 126014,
    "LoginID": null,
    "FirstName": "man",
    "LastName": null,
    "StartDate": "2021-08-18T11:35:19.713",
    "Organization": "Benchmark ESG",
    "Location": "Bangalore",
    "Title": null,
    "Email": null,
    "IsActive": "1",
    "Phone": null,
    "supervisor": null
  },
  {
    "EmployeeID": 126015,
    "LoginID": null,
    "FirstName": "gen",
    "LastName": null,
    "StartDate": "2021-08-20T01:55:52.453",
    "Organization": "Benchmark ESG",
    "Location": "Bangalore",
    "Title": null,
    "Email": null,
    "IsActive": "1",
    "Phone": null,
    "supervisor": null
  },
  {
    "EmployeeID": 126016,
    "LoginID": "7995691526",
    "FirstName": "Karthik",
    "LastName": "Allu",
    "StartDate": "2021-08-25T00:00:00",
    "Organization": "Benchmark ESG",
    "Location": "Bangalore",
    "Title": "Associate",
    "Email": "allurukarthik01@gmail.com",
    "IsActive": "1",
    "Phone": null,
    "supervisor": null
  },
  {
    "EmployeeID": 126017,
    "LoginID": null,
    "FirstName": "gensuite",
    "LastName": "benchmark",
    "StartDate": null,
    "Organization": "Benchmark ESG",
    "Location": "Bangalore",
    "Title": null,
    "Email": null,
    "IsActive": "1",
    "Phone": null,
    "supervisor": null
  },
  {
    "EmployeeID": 126018,
    "LoginID": null,
    "FirstName": "JONAM",
    "LastName": null,
    "StartDate": null,
    "Organization": "Benchmark ESG",
    "Location": "Bangalore",
    "Title": null,
    "Email": null,
    "IsActive": "1",
    "Phone": null,
    "supervisor": null
  },
  {
    "EmployeeID": 126020,
    "LoginID": null,
    "FirstName": "gensuite",
    "LastName": "benchmark",
    "StartDate": null,
    "Organization": "Benchmark ESG",
    "Location": "Bangalore",
    "Title": null,
    "Email": null,
    "IsActive": "1",
    "Phone": null,
    "supervisor": null
  },
  {
    "EmployeeID": 126026,
    "LoginID": "",
    "FirstName": "Manoj",
    "LastName": "",
    "StartDate": "2021-09-08T00:00:00",
    "Organization": "Benchmark ESG",
    "Location": "Bangalore",
    "Title": "",
    "Email": "vmanoj@gmail.com",
    "IsActive": "1",
    "Phone": "",
    "supervisor": null
  },
  {
    "EmployeeID": 126027,
    "LoginID": "9486758",
    "FirstName": "Tony",
    "LastName": "Parker",
    "StartDate": "2021-09-09T00:00:00",
    "Organization": "Benchmark ESG",
    "Location": "Bangalore",
    "Title": "Trainee",
    "Email": "tony.stark@gmail.com",
    "IsActive": "1",
    "Phone": "3456789098",
    "supervisor": null
  },
  {
    "EmployeeID": 126031,
    "LoginID": "321",
    "FirstName": "naruto",
    "LastName": "uzumaki",
    "StartDate": "2021-09-20T06:16:27.86",
    "Organization": "Benchmark ESG",
    "Location": "Bangalore",
    "Title": "Associate",
    "Email": "naruto@gmail.com",
    "IsActive": "1",
    "Phone": "123123",
    "supervisor": null
  },
  {
    "EmployeeID": 126032,
    "LoginID": "12333",
    "FirstName": "rich",
    "LastName": "rak",
    "StartDate": "2017-01-05T00:00:00",
    "Organization": "Benchmark ESG",
    "Location": "Bangalore",
    "Title": "Associate",
    "Email": "richo@gmail.com",
    "IsActive": "1",
    "Phone": "12313",
    "supervisor": null
  },
  {
    "EmployeeID": 126033,
    "LoginID": "12332",
    "FirstName": "Tom",
    "LastName": "cruise",
    "StartDate": "2021-09-21T03:28:58.953",
    "Organization": "Benchmark ESG",
    "Location": "Bangalore",
    "Title": null,
    "Email": "tom@gmail.com",
    "IsActive": "1",
    "Phone": "123444",
    "supervisor": null
  },
  {
    "EmployeeID": 126034,
    "LoginID": "45622",
    "FirstName": "John",
    "LastName": "jemmy",
    "StartDate": "2021-09-21T03:28:58.953",
    "Organization": "Benchmark ESG",
    "Location": "Bangalore",
    "Title": null,
    "Email": "john@gmail.com",
    "IsActive": "1",
    "Phone": "123444",
    "supervisor": null
  },
  {
    "EmployeeID": 126035,
    "LoginID": "74327",
    "FirstName": "Devid",
    "LastName": "beck",
    "StartDate": "2021-09-21T03:28:58.953",
    "Organization": "Benchmark ESG",
    "Location": "Bangalore",
    "Title": null,
    "Email": "devid@gmail.com",
    "IsActive": "1",
    "Phone": "123444",
    "supervisor": null
  },
  {
    "EmployeeID": 126036,
    "LoginID": "123211",
    "FirstName": "Ferry",
    "LastName": "furnadis",
    "StartDate": "2021-09-21T05:02:25.217",
    "Organization": "Benchmark ESG",
    "Location": "Bangalore",
    "Title": null,
    "Email": "tom@gmail.com",
    "IsActive": "1",
    "Phone": "123444",
    "supervisor": null
  },
  {
    "EmployeeID": 126037,
    "LoginID": "8989765432",
    "FirstName": "trdc",
    "LastName": "",
    "StartDate": "2021-09-09T00:00:00",
    "Organization": "Benchmark ESG",
    "Location": "Bangalore",
    "Title": "Associate",
    "Email": "abc@gmail",
    "IsActive": "1",
    "Phone": null,
    "supervisor": null
  },
  {
    "EmployeeID": 126038,
    "LoginID": "6767545432",
    "FirstName": "gd",
    "LastName": "",
    "StartDate": "2021-09-09T00:00:00",
    "Organization": "Benchmark ESG",
    "Location": "Bangalore",
    "Title": "Associate",
    "Email": "tes*t@gmail",
    "IsActive": "1",
    "Phone": null,
    "supervisor": null
  },
  {
    "EmployeeID": 126039,
    "LoginID": "6767545432",
    "FirstName": "gd",
    "LastName": "",
    "StartDate": "2021-09-09T00:00:00",
    "Organization": "Benchmark ESG",
    "Location": "Bangalore",
    "Title": "Associate",
    "Email": "tes*t@gmail",
    "IsActive": "1",
    "Phone": null,
    "supervisor": null
  },
  {
    "EmployeeID": 126040,
    "LoginID": "6767545432",
    "FirstName": "gd",
    "LastName": "",
    "StartDate": "2021-09-09T00:00:00",
    "Organization": "Benchmark ESG",
    "Location": "Bangalore",
    "Title": "Associate",
    "Email": "tes*t@gmail",
    "IsActive": "1",
    "Phone": null,
    "supervisor": null
  },
  {
    "EmployeeID": 126041,
    "LoginID": "6767675454",
    "FirstName": "ec",
    "LastName": "",
    "StartDate": "2021-09-14T00:00:00",
    "Organization": "Benchmark ESG",
    "Location": "Bangalore",
    "Title": "Associate",
    "Email": "abc@gmail",
    "IsActive": "1",
    "Phone": null,
    "supervisor": null
  },
  {
    "EmployeeID": 126042,
    "LoginID": "6565432123",
    "FirstName": "gd",
    "LastName": "",
    "StartDate": "2021-09-02T00:00:00",
    "Organization": "Benchmark ESG",
    "Location": "Bangalore",
    "Title": "Associate",
    "Email": "abc@gmail",
    "IsActive": "1",
    "Phone": null,
    "supervisor": null
  },
  {
    "EmployeeID": 126043,
    "LoginID": "7897896543",
    "FirstName": "ty",
    "LastName": "",
    "StartDate": "2021-09-06T00:00:00",
    "Organization": "Benchmark ESG",
    "Location": "Bangalore",
    "Title": "Associate",
    "Email": "abc@gmail",
    "IsActive": "1",
    "Phone": null,
    "supervisor": null
  },
  {
    "EmployeeID": 126047,
    "LoginID": "5678",
    "FirstName": "Jiya",
    "LastName": "Pise",
    "StartDate": "2020-08-03T00:00:00",
    "Organization": "Benchmark ESG",
    "Location": "Bangalore",
    "Title": "Tester",
    "Email": "test16@gmail.com",
    "IsActive": "1",
    "Phone": "7896543210",
    "supervisor": null
  },
  {
    "EmployeeID": 126048,
    "LoginID": "7890",
    "FirstName": "mina",
    "LastName": "Shahane",
    "StartDate": "2021-05-31T00:00:00",
    "Organization": "Benchmark ESG",
    "Location": "Bangalore",
    "Title": "Hr",
    "Email": "test17@gmail.com",
    "IsActive": "1",
    "Phone": "7689543021",
    "supervisor": null
  },
  {
    "EmployeeID": 126052,
    "LoginID": "7890",
    "FirstName": "batman",
    "LastName": "Pise",
    "StartDate": "2021-05-31T00:00:00",
    "Organization": "Benchmark ESG",
    "Location": "Bangalore",
    "Title": "Hr",
    "Email": "test19@gmail.com",
    "IsActive": "1",
    "Phone": "7689543021",
    "supervisor": null
  },
  {
    "EmployeeID": 126058,
    "LoginID": "7995691526",
    "FirstName": "Karthik",
    "LastName": "Allu",
    "StartDate": "2021-09-28T00:00:00",
    "Organization": "Benchmark ESG",
    "Location": "Bangalore",
    "Title": "Associate",
    "Email": "allurukarthik01@gmail.com",
    "IsActive": "1",
    "Phone": null,
    "supervisor": null
  },
  {
    "EmployeeID": 126059,
    "LoginID": "7995691526",
    "FirstName": "Karthik",
    "LastName": "Allu",
    "StartDate": "2021-09-28T00:00:00",
    "Organization": "Benchmark ESG",
    "Location": "Bangalore",
    "Title": "Associate",
    "Email": "allurukarthik01@gmail.com",
    "IsActive": "1",
    "Phone": null,
    "supervisor": null
  },
  {
    "EmployeeID": 126066,
    "LoginID": "",
    "FirstName": "Shreya",
    "LastName": "Shahane",
    "StartDate": null,
    "Organization": "Benchmark ESG",
    "Location": "Bangalore",
    "Title": "",
    "Email": "shreya@gmail.com",
    "IsActive": "1",
    "Phone": "7689054321",
    "supervisor": null
  },
  {
    "EmployeeID": 126073,
    "LoginID": "7995691526",
    "FirstName": "kar",
    "LastName": "Allu",
    "StartDate": "2021-10-01T00:00:00",
    "Organization": "Benchmark ESG",
    "Location": "Bangalore",
    "Title": "Associate",
    "Email": "alluru01@gmail.com",
    "IsActive": "1",
    "Phone": "234567899",
    "supervisor": null
  },
  {
    "EmployeeID": 126106,
    "LoginID": null,
    "FirstName": "Tony",
    "LastName": "Stark",
    "StartDate": "2021-06-16T00:00:00",
    "Organization": "Benchmark ESG",
    "Location": "Bangalore",
    "Title": "Trainee",
    "Email": "tony.stark@gmail.com",
    "IsActive": "1",
    "Phone": null,
    "supervisor": null
  },
  {
    "EmployeeID": 126112,
    "LoginID": null,
    "FirstName": "Tony",
    "LastName": "Stark",
    "StartDate": "2021-06-24T00:00:00",
    "Organization": "Benchmark ESG",
    "Location": "Bangalore",
    "Title": "Trainee",
    "Email": "tony.stark@gmail.com",
    "IsActive": "1",
    "Phone": null,
    "supervisor": null
  },
  {
    "EmployeeID": 126113,
    "LoginID": "9900",
    "FirstName": "Tony",
    "LastName": "Marvel",
    "StartDate": "2021-06-25T00:00:00",
    "Organization": "Benchmark ESG",
    "Location": "Bangalore",
    "Title": "Trainee",
    "Email": "tony.stark@gmail.com",
    "IsActive": "1",
    "Phone": "",
    "supervisor": null
  },
  {
    "EmployeeID": 126114,
    "LoginID": null,
    "FirstName": "Tony",
    "LastName": "Stark",
    "StartDate": "2021-06-24T00:00:00",
    "Organization": "Benchmark ESG",
    "Location": "Bangalore",
    "Title": "Trainee",
    "Email": "tony.stark@gmail.com",
    "IsActive": "1",
    "Phone": null,
    "supervisor": null
  },
  {
    "EmployeeID": 126115,
    "LoginID": null,
    "FirstName": "Tony",
    "LastName": "Stark",
    "StartDate": "2021-06-24T00:00:00",
    "Organization": "Benchmark ESG",
    "Location": "Bangalore",
    "Title": "Trainee",
    "Email": "tony.stark@gmail.com",
    "IsActive": "1",
    "Phone": null,
    "supervisor": null
  },
  {
    "EmployeeID": 126116,
    "LoginID": null,
    "FirstName": "Tony",
    "LastName": "Stark",
    "StartDate": "2021-06-24T00:00:00",
    "Organization": "Benchmark ESG",
    "Location": "Bangalore",
    "Title": "Trainee",
    "Email": "tony.stark@gmail.com",
    "IsActive": "1",
    "Phone": null,
    "supervisor": null
  },
  {
    "EmployeeID": 126117,
    "LoginID": null,
    "FirstName": "Tony",
    "LastName": "Stark",
    "StartDate": "2021-06-24T00:00:00",
    "Organization": "Benchmark ESG",
    "Location": "Bangalore",
    "Title": "Trainee",
    "Email": "tony.stark@gmail.com",
    "IsActive": "1",
    "Phone": null,
    "supervisor": null
  },
  {
    "EmployeeID": 126118,
    "LoginID": null,
    "FirstName": "Tony",
    "LastName": "Stark",
    "StartDate": "2021-06-24T00:00:00",
    "Organization": "Benchmark ESG",
    "Location": "Bangalore",
    "Title": "Trainee",
    "Email": "tony.stark@gmail.com",
    "IsActive": "1",
    "Phone": null,
    "supervisor": null
  },
  {
    "EmployeeID": 126119,
    "LoginID": null,
    "FirstName": "Tony",
    "LastName": "Stark",
    "StartDate": "2021-06-24T00:00:00",
    "Organization": "Benchmark ESG",
    "Location": "Bangalore",
    "Title": "Trainee",
    "Email": "tony.stark@gmail.com",
    "IsActive": "1",
    "Phone": null,
    "supervisor": null
  },
  {
    "EmployeeID": 126121,
    "LoginID": null,
    "FirstName": "Tony",
    "LastName": "Stark",
    "StartDate": "2021-06-24T00:00:00",
    "Organization": "Benchmark ESG",
    "Location": "Bangalore",
    "Title": "Trainee",
    "Email": "tony.stark@gmail.com",
    "IsActive": "1",
    "Phone": null,
    "supervisor": null
  },
  {
    "EmployeeID": 126132,
    "LoginID": "123456",
    "FirstName": "Tony",
    "LastName": "Stark",
    "StartDate": "2021-06-28T00:00:00",
    "Organization": "Benchmark ESG",
    "Location": "Bangalore",
    "Title": "Trainee",
    "Email": "tony.stark@gmail.com",
    "IsActive": "1",
    "Phone": null,
    "supervisor": null
  },
  {
    "EmployeeID": 126133,
    "LoginID": "123456",
    "FirstName": "Tony",
    "LastName": "Stark",
    "StartDate": "2021-06-28T00:00:00",
    "Organization": "Benchmark ESG",
    "Location": "Bangalore",
    "Title": "Trainee",
    "Email": "tony.stark11@gmail.com",
    "IsActive": "1",
    "Phone": null,
    "supervisor": null
  },
  {
    "EmployeeID": 126142,
    "LoginID": "1234576543",
    "FirstName": "hello",
    "LastName": "Ishitatest56",
    "StartDate": "2021-06-30T00:00:00",
    "Organization": "Benchmark ESG",
    "Location": "Bangalore",
    "Title": "Product Developer",
    "Email": "hello@gmail.com",
    "IsActive": "1",
    "Phone": null,
    "supervisor": null
  },
  {
    "EmployeeID": 126150,
    "LoginID": "1234576543",
    "FirstName": "hello",
    "LastName": "Ishitatest56",
    "StartDate": "2021-06-30T00:00:00",
    "Organization": "Benchmark ESG",
    "Location": "Bangalore",
    "Title": "Product Developer",
    "Email": "hello@gmail.com",
    "IsActive": "1",
    "Phone": "1234567898",
    "supervisor": null
  },
  {
    "EmployeeID": 126165,
    "LoginID": "123",
    "FirstName": "yes ok ",
    "LastName": "nono",
    "StartDate": "1900-01-01T00:00:00",
    "Organization": "Benchmark ESG",
    "Location": "Bangalore",
    "Title": "Trainee",
    "Email": "yesokno@gmail.com",
    "IsActive": "1",
    "Phone": null,
    "supervisor": null
  },
  {
    "EmployeeID": 126172,
    "LoginID": "1234578998",
    "FirstName": "hello",
    "LastName": "hello",
    "StartDate": "2021-06-30T00:00:00",
    "Organization": "Benchmark ESG",
    "Location": "Bangalore",
    "Title": "Associate",
    "Email": "hello@gmail.com",
    "IsActive": "1",
    "Phone": "7654569876",
    "supervisor": null
  },
  {
    "EmployeeID": 126177,
    "LoginID": "1234576543",
    "FirstName": "hello",
    "LastName": "Ishitatest",
    "StartDate": "2021-06-30T00:00:00",
    "Organization": "Benchmark ESG",
    "Location": "Bangalore",
    "Title": "Product Developer",
    "Email": "hello@gmail.com",
    "IsActive": "1",
    "Phone": "4567907612",
    "supervisor": null
  },
  {
    "EmployeeID": 126178,
    "LoginID": "12345",
    "FirstName": "James",
    "LastName": "Bond",
    "StartDate": "2021-06-04T00:00:00",
    "Organization": "Benchmark ESG",
    "Location": "Bangalore",
    "Title": "Trainee",
    "Email": "test@exae.com",
    "IsActive": "1",
    "Phone": "7564398576",
    "supervisor": null
  },
  {
    "EmployeeID": 126180,
    "LoginID": "888",
    "FirstName": "Ram",
    "LastName": "Sharma",
    "StartDate": "2021-06-11T00:00:00",
    "Organization": "Benchmark ESG",
    "Location": "Bangalore",
    "Title": "Associate",
    "Email": "ram22@gmail.com",
    "IsActive": "1",
    "Phone": "5628476901",
    "supervisor": null
  },
  {
    "EmployeeID": 126181,
    "LoginID": "888",
    "FirstName": "Ram",
    "LastName": "Sharma",
    "StartDate": "2021-06-11T00:00:00",
    "Organization": "Benchmark ESG",
    "Location": "Bangalore",
    "Title": "Associate",
    "Email": "ram22@gmail.com",
    "IsActive": "1",
    "Phone": "5628476901",
    "supervisor": null
  },
  {
    "EmployeeID": 126182,
    "LoginID": "12",
    "FirstName": "Steve",
    "LastName": "Stark",
    "StartDate": "2021-05-05T00:00:00",
    "Organization": "Benchmark ESG",
    "Location": "Bangalore",
    "Title": "Trainee",
    "Email": "ss@gmail.com",
    "IsActive": "1",
    "Phone": "9812639865",
    "supervisor": null
  },
  {
    "EmployeeID": 126183,
    "LoginID": "12",
    "FirstName": "Steve",
    "LastName": "Stark",
    "StartDate": "2021-05-05T00:00:00",
    "Organization": "Benchmark ESG",
    "Location": "Bangalore",
    "Title": "Trainee",
    "Email": "ss@gmail.com",
    "IsActive": "1",
    "Phone": "9812639865",
    "supervisor": null
  },
  {
    "EmployeeID": 126186,
    "LoginID": "219",
    "FirstName": "John",
    "LastName": "",
    "StartDate": "2021-06-29T00:00:00",
    "Organization": "Benchmark ESG",
    "Location": "Bangalore",
    "Title": "Trainee",
    "Email": "john@gmail.com",
    "IsActive": "1",
    "Phone": "4567328907",
    "supervisor": null
  },
  {
    "EmployeeID": 126193,
    "LoginID": "104",
    "FirstName": "James",
    "LastName": "",
    "StartDate": "2021-07-01T00:00:00",
    "Organization": "Benchmark ESG",
    "Location": "Bangalore",
    "Title": "Trainee",
    "Email": "jj@gmail.com",
    "IsActive": "1",
    "Phone": "1234567899",
    "supervisor": null
  },
  {
    "EmployeeID": 126201,
    "LoginID": "598123",
    "FirstName": "Jasper",
    "LastName": "",
    "StartDate": "2021-07-01T00:00:00",
    "Organization": "Benchmark ESG",
    "Location": "Bangalore",
    "Title": "Trainee",
    "Email": "test@j.com",
    "IsActive": "1",
    "Phone": "5678923456",
    "supervisor": null
  },
  {
    "EmployeeID": 126205,
    "LoginID": "578374",
    "FirstName": "James",
    "LastName": "",
    "StartDate": "2021-07-02T00:00:00",
    "Organization": "Benchmark ESG",
    "Location": "Bangalore",
    "Title": "Trainee",
    "Email": "james@gmail.com",
    "IsActive": "1",
    "Phone": "4567893456",
    "supervisor": null
  },
  {
    "EmployeeID": 126209,
    "LoginID": "68786",
    "FirstName": "Jasper",
    "LastName": "",
    "StartDate": "2021-06-27T00:00:00",
    "Organization": "Benchmark ESG",
    "Location": "Bangalore",
    "Title": "Trainee",
    "Email": "test@james.com",
    "IsActive": "1",
    "Phone": "4567891234",
    "supervisor": null
  },
  {
    "EmployeeID": 126217,
    "LoginID": "867898",
    "FirstName": "James",
    "LastName": "",
    "StartDate": "2021-07-05T00:00:00",
    "Organization": "Benchmark ESG",
    "Location": "Bangalore",
    "Title": "Trainee",
    "Email": "james@gmail.com",
    "IsActive": "1",
    "Phone": "4563826583",
    "supervisor": null
  },
  {
    "EmployeeID": 126222,
    "LoginID": "786905",
    "FirstName": "Sutton",
    "LastName": "",
    "StartDate": "2021-07-13T00:00:00",
    "Organization": "Benchmark ESG",
    "Location": "Bangalore",
    "Title": "",
    "Email": "hello@gmail.com",
    "IsActive": "1",
    "Phone": "3456846898",
    "supervisor": null
  },
  {
    "EmployeeID": 126227,
    "LoginID": "127",
    "FirstName": "Clark",
    "LastName": "Kent",
    "StartDate": null,
    "Organization": "Benchmark ESG",
    "Location": "Bangalore",
    "Title": null,
    "Email": null,
    "IsActive": "1",
    "Phone": null,
    "supervisor": null
  },
  {
    "EmployeeID": 126228,
    "LoginID": "127",
    "FirstName": "Clark",
    "LastName": "Kent",
    "StartDate": null,
    "Organization": "Benchmark ESG",
    "Location": "Bangalore",
    "Title": null,
    "Email": null,
    "IsActive": "1",
    "Phone": null,
    "supervisor": null
  },
  {
    "EmployeeID": 126229,
    "LoginID": "679",
    "FirstName": "Ram",
    "LastName": "Sharma",
    "StartDate": "2021-07-27T02:54:58.763",
    "Organization": "Benchmark ESG",
    "Location": "Bangalore",
    "Title": null,
    "Email": null,
    "IsActive": "1",
    "Phone": null,
    "supervisor": null
  },
  {
    "EmployeeID": 126230,
    "LoginID": "1232",
    "FirstName": "eff",
    "LastName": "ddd",
    "StartDate": "2021-07-26T00:00:00",
    "Organization": "Benchmark ESG",
    "Location": "Bangalore",
    "Title": "test",
    "Email": "giri.prasanth@gensuitellc",
    "IsActive": "1",
    "Phone": null,
    "supervisor": null
  },
  {
    "EmployeeID": 126233,
    "LoginID": "45696",
    "FirstName": "Tony",
    "LastName": "Stark",
    "StartDate": "2021-08-02T00:00:00",
    "Organization": "Benchmark ESG",
    "Location": "Bangalore",
    "Title": "Trainee",
    "Email": "tony.stark@gmail.com",
    "IsActive": "1",
    "Phone": "2365739275",
    "supervisor": null
  },
  {
    "EmployeeID": 126244,
    "LoginID": null,
    "FirstName": "gen",
    "LastName": null,
    "StartDate": "2021-08-18T11:23:38.7",
    "Organization": "Benchmark ESG",
    "Location": "Bangalore",
    "Title": null,
    "Email": null,
    "IsActive": "1",
    "Phone": null,
    "supervisor": null
  },
  {
    "EmployeeID": 126245,
    "LoginID": null,
    "FirstName": "man",
    "LastName": null,
    "StartDate": "2021-08-18T11:35:19.713",
    "Organization": "Benchmark ESG",
    "Location": "Bangalore",
    "Title": null,
    "Email": null,
    "IsActive": "1",
    "Phone": null,
    "supervisor": null
  },
  {
    "EmployeeID": 126246,
    "LoginID": null,
    "FirstName": "gen",
    "LastName": null,
    "StartDate": "2021-08-20T01:55:52.453",
    "Organization": "Benchmark ESG",
    "Location": "Bangalore",
    "Title": null,
    "Email": null,
    "IsActive": "1",
    "Phone": null,
    "supervisor": null
  },
  {
    "EmployeeID": 126247,
    "LoginID": null,
    "FirstName": "gen",
    "LastName": null,
    "StartDate": "2021-08-18T11:23:38.7",
    "Organization": "Benchmark ESG",
    "Location": "Bangalore",
    "Title": null,
    "Email": null,
    "IsActive": "1",
    "Phone": null,
    "supervisor": null
  },
  {
    "EmployeeID": 126248,
    "LoginID": null,
    "FirstName": "man",
    "LastName": null,
    "StartDate": "2021-08-18T11:35:19.713",
    "Organization": "Benchmark ESG",
    "Location": "Bangalore",
    "Title": null,
    "Email": null,
    "IsActive": "1",
    "Phone": null,
    "supervisor": null
  },
  {
    "EmployeeID": 126249,
    "LoginID": null,
    "FirstName": "gen",
    "LastName": null,
    "StartDate": "2021-08-20T01:55:52.453",
    "Organization": "Benchmark ESG",
    "Location": "Bangalore",
    "Title": null,
    "Email": null,
    "IsActive": "1",
    "Phone": null,
    "supervisor": null
  },
  {
    "EmployeeID": 126250,
    "LoginID": null,
    "FirstName": "gd",
    "LastName": null,
    "StartDate": "2019-06-06T00:00:00",
    "Organization": "Benchmark ESG",
    "Location": "Bangalore",
    "Title": null,
    "Email": null,
    "IsActive": "1",
    "Phone": null,
    "supervisor": null
  },
  {
    "EmployeeID": 126251,
    "LoginID": null,
    "FirstName": "Parker",
    "LastName": null,
    "StartDate": "2020-06-05T00:00:00",
    "Organization": "Benchmark ESG",
    "Location": "Bangalore",
    "Title": null,
    "Email": null,
    "IsActive": "1",
    "Phone": null,
    "supervisor": null
  },
  {
    "EmployeeID": 126253,
    "LoginID": null,
    "FirstName": "gen",
    "LastName": null,
    "StartDate": "2021-08-18T11:23:38.7",
    "Organization": "Benchmark ESG",
    "Location": "Bangalore",
    "Title": null,
    "Email": null,
    "IsActive": "1",
    "Phone": null,
    "supervisor": null
  },
  {
    "EmployeeID": 126254,
    "LoginID": null,
    "FirstName": "man",
    "LastName": null,
    "StartDate": "2021-08-18T11:35:19.713",
    "Organization": "Benchmark ESG",
    "Location": "Bangalore",
    "Title": null,
    "Email": null,
    "IsActive": "1",
    "Phone": null,
    "supervisor": null
  },
  {
    "EmployeeID": 126255,
    "LoginID": null,
    "FirstName": "gen",
    "LastName": null,
    "StartDate": "2021-08-20T01:55:52.453",
    "Organization": "Benchmark ESG",
    "Location": "Bangalore",
    "Title": null,
    "Email": null,
    "IsActive": "1",
    "Phone": null,
    "supervisor": null
  },
  {
    "EmployeeID": 126256,
    "LoginID": "7995691526",
    "FirstName": "Karthik",
    "LastName": "Allu",
    "StartDate": "2021-08-25T00:00:00",
    "Organization": "Benchmark ESG",
    "Location": "Bangalore",
    "Title": "Associate",
    "Email": "allurukarthik01@gmail.com",
    "IsActive": "1",
    "Phone": null,
    "supervisor": null
  },
  {
    "EmployeeID": 126257,
    "LoginID": null,
    "FirstName": "gensuite",
    "LastName": "benchmark",
    "StartDate": null,
    "Organization": "Benchmark ESG",
    "Location": "Bangalore",
    "Title": null,
    "Email": null,
    "IsActive": "1",
    "Phone": null,
    "supervisor": null
  },
  {
    "EmployeeID": 126258,
    "LoginID": null,
    "FirstName": "JONAM",
    "LastName": null,
    "StartDate": null,
    "Organization": "Benchmark ESG",
    "Location": "Bangalore",
    "Title": null,
    "Email": null,
    "IsActive": "1",
    "Phone": null,
    "supervisor": null
  },
  {
    "EmployeeID": 126260,
    "LoginID": null,
    "FirstName": "gensuite",
    "LastName": "benchmark",
    "StartDate": null,
    "Organization": "Benchmark ESG",
    "Location": "Bangalore",
    "Title": null,
    "Email": null,
    "IsActive": "1",
    "Phone": null,
    "supervisor": null
  },
  {
    "EmployeeID": 126266,
    "LoginID": "",
    "FirstName": "Manoj",
    "LastName": "",
    "StartDate": "2021-09-08T00:00:00",
    "Organization": "Benchmark ESG",
    "Location": "Bangalore",
    "Title": "",
    "Email": "vmanoj@gmail.com",
    "IsActive": "1",
    "Phone": "",
    "supervisor": null
  },
  {
    "EmployeeID": 126267,
    "LoginID": "9486758",
    "FirstName": "Tony",
    "LastName": "Parker",
    "StartDate": "2021-09-09T00:00:00",
    "Organization": "Benchmark ESG",
    "Location": "Bangalore",
    "Title": "Trainee",
    "Email": "tony.stark@gmail.com",
    "IsActive": "1",
    "Phone": "3456789098",
    "supervisor": null
  },
  {
    "EmployeeID": 126271,
    "LoginID": null,
    "FirstName": "TestR",
    "LastName": "RR",
    "StartDate": "2017-12-06T00:00:00",
    "Organization": "Benchmark ESG",
    "Location": "Bangalore",
    "Title": null,
    "Email": "testr@gmail.com",
    "IsActive": "1",
    "Phone": null,
    "supervisor": null
  },
  {
    "EmployeeID": 126272,
    "LoginID": "321",
    "FirstName": "naruto",
    "LastName": "uzumaki",
    "StartDate": "2021-09-20T06:16:27.86",
    "Organization": "Benchmark ESG",
    "Location": "Bangalore",
    "Title": "Associate",
    "Email": "naruto@gmail.com",
    "IsActive": "1",
    "Phone": "123123",
    "supervisor": null
  },
  {
    "EmployeeID": 126273,
    "LoginID": "12333",
    "FirstName": "rich",
    "LastName": "rak",
    "StartDate": "2017-01-05T00:00:00",
    "Organization": "Benchmark ESG",
    "Location": "Bangalore",
    "Title": "Associate",
    "Email": "richo@gmail.com",
    "IsActive": "1",
    "Phone": "12313",
    "supervisor": null
  },
  {
    "EmployeeID": 126274,
    "LoginID": "12332",
    "FirstName": "Tom",
    "LastName": "cruise",
    "StartDate": "2021-09-21T03:28:58.953",
    "Organization": "Benchmark ESG",
    "Location": "Bangalore",
    "Title": null,
    "Email": "tom@gmail.com",
    "IsActive": "1",
    "Phone": "123444",
    "supervisor": null
  },
  {
    "EmployeeID": 126275,
    "LoginID": "45622",
    "FirstName": "John",
    "LastName": "jemmy",
    "StartDate": "2021-09-21T03:28:58.953",
    "Organization": "Benchmark ESG",
    "Location": "Bangalore",
    "Title": null,
    "Email": "john@gmail.com",
    "IsActive": "1",
    "Phone": "123444",
    "supervisor": null
  },
  {
    "EmployeeID": 126276,
    "LoginID": "74327",
    "FirstName": "Devid",
    "LastName": "beck",
    "StartDate": "2021-09-21T03:28:58.953",
    "Organization": "Benchmark ESG",
    "Location": "Bangalore",
    "Title": null,
    "Email": "devid@gmail.com",
    "IsActive": "1",
    "Phone": "123444",
    "supervisor": null
  },
  {
    "EmployeeID": 126277,
    "LoginID": "123211",
    "FirstName": "Ferry",
    "LastName": "furnadis",
    "StartDate": "2021-09-21T05:02:25.217",
    "Organization": "Benchmark ESG",
    "Location": "Bangalore",
    "Title": null,
    "Email": "tom@gmail.com",
    "IsActive": "1",
    "Phone": "123444",
    "supervisor": null
  },
  {
    "EmployeeID": 126278,
    "LoginID": "8989765432",
    "FirstName": "trdc",
    "LastName": "",
    "StartDate": "2021-09-09T00:00:00",
    "Organization": "Benchmark ESG",
    "Location": "Bangalore",
    "Title": "Associate",
    "Email": "abc@gmail",
    "IsActive": "1",
    "Phone": null,
    "supervisor": null
  },
  {
    "EmployeeID": 126279,
    "LoginID": "6767545432",
    "FirstName": "gd",
    "LastName": "",
    "StartDate": "2021-09-09T00:00:00",
    "Organization": "Benchmark ESG",
    "Location": "Bangalore",
    "Title": "Associate",
    "Email": "tes*t@gmail",
    "IsActive": "1",
    "Phone": null,
    "supervisor": null
  },
  {
    "EmployeeID": 126280,
    "LoginID": "6767545432",
    "FirstName": "gd",
    "LastName": "",
    "StartDate": "2021-09-09T00:00:00",
    "Organization": "Benchmark ESG",
    "Location": "Bangalore",
    "Title": "Associate",
    "Email": "tes*t@gmail",
    "IsActive": "1",
    "Phone": null,
    "supervisor": null
  },
  {
    "EmployeeID": 126281,
    "LoginID": "6767545432",
    "FirstName": "gd",
    "LastName": "",
    "StartDate": "2021-09-09T00:00:00",
    "Organization": "Benchmark ESG",
    "Location": "Bangalore",
    "Title": "Associate",
    "Email": "tes*t@gmail",
    "IsActive": "1",
    "Phone": null,
    "supervisor": null
  },
  {
    "EmployeeID": 126282,
    "LoginID": "6767675454",
    "FirstName": "ec",
    "LastName": "",
    "StartDate": "2021-09-14T00:00:00",
    "Organization": "Benchmark ESG",
    "Location": "Bangalore",
    "Title": "Associate",
    "Email": "abc@gmail",
    "IsActive": "1",
    "Phone": null,
    "supervisor": null
  },
  {
    "EmployeeID": 126283,
    "LoginID": "6767675454",
    "FirstName": "ec",
    "LastName": "",
    "StartDate": "2021-09-14T00:00:00",
    "Organization": "Benchmark ESG",
    "Location": "Bangalore",
    "Title": "Associate",
    "Email": "abc@gmail",
    "IsActive": "1",
    "Phone": null,
    "supervisor": null
  },
  {
    "EmployeeID": 126284,
    "LoginID": "7897896543",
    "FirstName": "ty",
    "LastName": "",
    "StartDate": "2021-09-06T00:00:00",
    "Organization": "Benchmark ESG",
    "Location": "Bangalore",
    "Title": "Associate",
    "Email": "abc@gmail",
    "IsActive": "1",
    "Phone": null,
    "supervisor": null
  },
  {
    "EmployeeID": 126288,
    "LoginID": "5678",
    "FirstName": "Jiya",
    "LastName": "Pise",
    "StartDate": "2020-08-03T00:00:00",
    "Organization": "Benchmark ESG",
    "Location": "Bangalore",
    "Title": "Tester",
    "Email": "test16@gmail.com",
    "IsActive": "1",
    "Phone": "7896543210",
    "supervisor": null
  },
  {
    "EmployeeID": 126289,
    "LoginID": "7890",
    "FirstName": "mina",
    "LastName": "Shahane",
    "StartDate": "2021-05-31T00:00:00",
    "Organization": "Benchmark ESG",
    "Location": "Bangalore",
    "Title": "Hr",
    "Email": "test17@gmail.com",
    "IsActive": "1",
    "Phone": "7689543021",
    "supervisor": null
  },
  {
    "EmployeeID": 126293,
    "LoginID": "7890",
    "FirstName": "batman",
    "LastName": "Pise",
    "StartDate": "2021-05-31T00:00:00",
    "Organization": "Benchmark ESG",
    "Location": "Bangalore",
    "Title": "Hr",
    "Email": "test19@gmail.com",
    "IsActive": "1",
    "Phone": "7689543021",
    "supervisor": null
  },
  {
    "EmployeeID": 126299,
    "LoginID": "7995691526",
    "FirstName": "Karthik",
    "LastName": "Allu",
    "StartDate": "2021-09-28T00:00:00",
    "Organization": "Benchmark ESG",
    "Location": "Bangalore",
    "Title": "Associate",
    "Email": "allurukarthik01@gmail.com",
    "IsActive": "1",
    "Phone": null,
    "supervisor": null
  },
  {
    "EmployeeID": 126300,
    "LoginID": "7995691526",
    "FirstName": "Karthik",
    "LastName": "Allu",
    "StartDate": "2021-09-28T00:00:00",
    "Organization": "Benchmark ESG",
    "Location": "Bangalore",
    "Title": "Associate",
    "Email": "allurukarthik01@gmail.com",
    "IsActive": "1",
    "Phone": null,
    "supervisor": null
  },
  {
    "EmployeeID": 126307,
    "LoginID": "",
    "FirstName": "Shreya",
    "LastName": "Shahane",
    "StartDate": null,
    "Organization": "Benchmark ESG",
    "Location": "Bangalore",
    "Title": "",
    "Email": "shreya@gmail.com",
    "IsActive": "1",
    "Phone": "7689054321",
    "supervisor": null
  },
  {
    "EmployeeID": 126314,
    "LoginID": "7995691526",
    "FirstName": "Karthik",
    "LastName": "Allu",
    "StartDate": "2021-10-01T00:00:00",
    "Organization": "Benchmark ESG",
    "Location": "Bangalore",
    "Title": "Associate",
    "Email": "allurukarthik01@gmail.com",
    "IsActive": "1",
    "Phone": null,
    "supervisor": null
  },
  {
    "EmployeeID": 126331,
    "LoginID": null,
    "FirstName": "mira",
    "LastName": null,
    "StartDate": null,
    "Organization": "Benchmark ESG",
    "Location": "Bangalore",
    "Title": null,
    "Email": null,
    "IsActive": "1",
    "Phone": null,
    "supervisor": null
  },
  {
    "EmployeeID": 126344,
    "LoginID": null,
    "FirstName": "siya",
    "LastName": "mishra",
    "StartDate": null,
    "Organization": "Benchmark ESG",
    "Location": "Bangalore",
    "Title": "Product Developer",
    "Email": "siya@gmail.com",
    "IsActive": "1",
    "Phone": null,
    "supervisor": null
  },
  {
    "EmployeeID": 126345,
    "LoginID": null,
    "FirstName": "diya",
    "LastName": "park",
    "StartDate": null,
    "Organization": "Benchmark ESG",
    "Location": "Bangalore",
    "Title": "Product Developer",
    "Email": "s@gmail.com",
    "IsActive": "1",
    "Phone": null,
    "supervisor": null
  },
  {
    "EmployeeID": 126349,
    "LoginID": null,
    "FirstName": "riya",
    "LastName": "park",
    "StartDate": null,
    "Organization": "Benchmark ESG",
    "Location": "Bangalore",
    "Title": "Product Developer",
    "Email": "riya@gmail.com",
    "IsActive": "1",
    "Phone": null,
    "supervisor": null
  },
  {
    "EmployeeID": 126356,
    "LoginID": "1234123423",
    "FirstName": "abc",
    "LastName": "",
    "StartDate": "2021-09-27T00:00:00",
    "Organization": "Benchmark ESG",
    "Location": "Bangalore",
    "Title": "Trainee",
    "Email": "abc@gmail",
    "IsActive": "1",
    "Phone": null,
    "supervisor": null
  },
  {
    "EmployeeID": 126388,
    "LoginID": "7995691526",
    "FirstName": "Karthik",
    "LastName": "",
    "StartDate": "2021-10-19T00:00:00",
    "Organization": "Benchmark ESG",
    "Location": "Bangalore",
    "Title": "Associate",
    "Email": "allurukarthik01@gmail.com",
    "IsActive": "1",
    "Phone": null,
    "supervisor": null
  },
  {
    "EmployeeID": 126416,
    "LoginID": null,
    "FirstName": "Tony",
    "LastName": "Stark",
    "StartDate": "2021-06-16T00:00:00",
    "Organization": "Benchmark ESG",
    "Location": "Bangalore",
    "Title": "Trainee",
    "Email": "tony.stark@gmail.com",
    "IsActive": "1",
    "Phone": null,
    "supervisor": null
  },
  {
    "EmployeeID": 126422,
    "LoginID": null,
    "FirstName": "Tony",
    "LastName": "Stark",
    "StartDate": "2021-06-24T00:00:00",
    "Organization": "Benchmark ESG",
    "Location": "Bangalore",
    "Title": "Trainee",
    "Email": "tony.stark@gmail.com",
    "IsActive": "1",
    "Phone": null,
    "supervisor": null
  },
  {
    "EmployeeID": 126423,
    "LoginID": null,
    "FirstName": "Tony",
    "LastName": "Stark",
    "StartDate": "2021-06-24T00:00:00",
    "Organization": "Benchmark ESG",
    "Location": "Bangalore",
    "Title": "Trainee",
    "Email": "tony.stark@gmail.com",
    "IsActive": "1",
    "Phone": null,
    "supervisor": null
  }
]
